Metadata-Version: 1.0
Name: shapwrap
Version: 0.1.0
Summary: A wrapper for SHAP library. Makes experimenting faster and extends functionality. 
Home-page: https://github.com/d-kz/shapwrap
Author: Denis Kazakov
Author-email: deka6994@colorado.edu
License: UNKNOWN
Platform: UNKNOWN
